[
  {
    "ContainingType": "JegyAPI.Controllers.ProductController",
    "Method": "Get",
    "RelativePath": "jegy",
    "HttpMethod": "GET",
    "IsController": true,
    "Order": 0,
    "Parameters": [],
    "ReturnTypes": [
      {
        "Type": "System.Collections.Generic.List\u00601[[JegyAPI.Models.Jegy, JegyAPI, Version=1.0.0.0, Culture=neutral, PublicKeyToken=null]]",
        "MediaTypes": [
          "text/plain",
          "application/json",
          "text/json"
        ],
        "StatusCode": 200
      }
    ]
  },
  {
    "ContainingType": "JegyAPI.Controllers.ProductController",
    "Method": "Post",
    "RelativePath": "jegy",
    "HttpMethod": "POST",
    "IsController": true,
    "Order": 0,
    "Parameters": [
      {
        "Name": "ertekeles",
        "Type": "System.Int32",
        "IsRequired": false
      },
      {
        "Name": "leiras",
        "Type": "System.String",
        "IsRequired": false
      }
    ],
    "ReturnTypes": [
      {
        "Type": "JegyAPI.Models.Jegy",
        "MediaTypes": [
          "text/plain",
          "application/json",
          "text/json"
        ],
        "StatusCode": 200
      }
    ]
  },
  {
    "ContainingType": "JegyAPI.Controllers.ProductController",
    "Method": "Put",
    "RelativePath": "jegy",
    "HttpMethod": "PUT",
    "IsController": true,
    "Order": 0,
    "Parameters": [
      {
        "Name": "Id",
        "Type": "System.Guid",
        "IsRequired": false
      },
      {
        "Name": "UjErtekeles",
        "Type": "System.Int32",
        "IsRequired": false
      },
      {
        "Name": "UjLeiras",
        "Type": "System.String",
        "IsRequired": false
      }
    ],
    "ReturnTypes": [
      {
        "Type": "JegyAPI.Models.Jegy",
        "MediaTypes": [
          "text/plain",
          "application/json",
          "text/json"
        ],
        "StatusCode": 200
      }
    ]
  },
  {
    "ContainingType": "JegyAPI.Controllers.ProductController",
    "Method": "Delete",
    "RelativePath": "jegy",
    "HttpMethod": "DELETE",
    "IsController": true,
    "Order": 0,
    "Parameters": [
      {
        "Name": "Id",
        "Type": "System.Guid",
        "IsRequired": false
      }
    ],
    "ReturnTypes": [
      {
        "Type": "System.String",
        "MediaTypes": [
          "text/plain",
          "application/json",
          "text/json"
        ],
        "StatusCode": 200
      }
    ]
  }
]